{
    "pack": {
        "id": "sayuri.me.voidascendedplayz",
        "name": "Sayuri",
        "characters": [
            "Sayuri"
        ],
        "authors": [
            "VoidAscendedPlayz"
        ],
        "kind": [
            "Characters"
        ],
        "source": "",
        "dddg2Path": "",
        "description": "[ Created in May 2024 ]",
        "preview": [
            "https://voidascendedplayz.github.io/dddg/characters_pack_4/sayuri.me.voidascendedplayz/1a.png",
            "https://voidascendedplayz.github.io/dddg/characters_pack_4/sayuri.me.voidascendedplayz/expressions/a.png"
        ],
        "searchWords": []
    },
    "authors": {}
}