{
    "$schema": "https://raw.githubusercontent.com/edave64/doki-doki-dialog-generator-pack-format/master/src/v1/schema.json",
    "packId": "hibari.me.voidasendedplayz",
    "packCredits": "",
    "packName": "Hibari",
    "authors": [],
    "id": "ddlc.plus.hibari.me",
    "name": "Hibari",
    "chibi": "./chibi.png",
    "styles": [
        {
            "name": "dark",
            "label": "Dark"
        }
    ],
    "heads": {
        "straight": [
            "./a.png",
            "./b.png",
            "./c.png",
            "./d.png",
            "./e.png",
            "./f.png",
            "./g.png",
            "./h.png",
            "./i.png",
            "./j.png",
            "./k.png",
            "./l.png",
            "./m.png",
            "./n.png",
            "./o.png",
            "./p.png",
            "./q.png",
            "./r.png",
            "./s.png",
            "./t.png",
            "./u.png",
            "./v.png",
            "./w.png",
            "./x.png",
            "./y.png",
            "./z.png"
        ]
    },
    "poses": [
        {
            "name": "Uniform Pose 1",
            "style": "dark",
            "compatibleHeads": [
                "straight"
            ],
            "static": "./1.png"
        },
        {
            "name": "Uniform Pose 2",
            "style": "dark",
            "compatibleHeads": [
                "straight"
            ],
            "static": "./2.png"
        },
        {
            "name": "Uniform Pose 3",
            "style": "dark",
            "compatibleHeads": [
                "straight"
            ],
            "static": "./3.png"
        },
        {
            "name": "Uniform Pose 4",
            "style": "dark",
            "compatibleHeads": [
                "straight"
            ],
            "static": "./4.png"
        },
        {
            "name": "Uniform Pose 5",
            "style": "dark",
            "compatibleHeads": [
                "straight"
            ],
            "static": "./5.png"
        },
        {
            "name": "Uniform Pose 6",
            "style": "dark",
            "compatibleHeads": [
                "straight"
            ],
            "static": "./6.png"
        },
        {
            "name": "Casual Pose 1",
            "style": "dark",
            "compatibleHeads": [
                "straight"
            ],
            "static": "./7.png"
        },
        {
            "name": "Casual Pose 2",
            "style": "dark",
            "compatibleHeads": [
                "straight"
            ],
            "static": "./8.png"
        },
        {
            "name": "Casual Pose 3",
            "style": "dark",
            "compatibleHeads": [
                "straight"
            ],
            "static": "./9.png"
        },
        {
            "name": "Casual Pose 4",
            "style": "dark",
            "compatibleHeads": [
                "straight"
            ],
            "static": "./10.png"
        },
        {
            "name": "Casual Pose 5",
            "style": "dark",
            "compatibleHeads": [
                "straight"
            ],
            "static": "./11.png"
        },
        {
            "name": "Casual Pose 6",
            "style": "dark",
            "compatibleHeads": [
                "straight"
            ],
            "static": "./12.png"
        }
    ]
}